actionblocks/a.pyd
actionblocks/b.pyd
actionblocks/c.pyd
actionblocks-0.0.3.dist-info/METADATA
actionblocks-0.0.3.dist-info/WHEEL
actionblocks-0.0.3.dist-info/top_level.txt
actionblocks-0.0.3.dist-info/RECORD
