Metadata-Version: 2.1
Name: actionblocks
Version: 0.0.3
Summary: D helper
Home-page: 
Author: actionblocks
Author-email: actionblocks@gmail.com
License: Apache 2.0
Platform: Windows Only
Classifier: Programming Language :: Python :: 3
Classifier: Operating System :: Microsoft :: Windows
Requires-Dist: tdrpa.tdworker
